maestral_cocoa/__init__.py
maestral_cocoa/__main__.py
maestral_cocoa/activity.py
maestral_cocoa/app.py
maestral_cocoa/autostart.py
maestral_cocoa/bandwidth.py
maestral_cocoa/bandwidth_gui.py
maestral_cocoa/constants.py
maestral_cocoa/dbx_location_dialog.py
maestral_cocoa/dialogs.py
maestral_cocoa/selective_sync.py
maestral_cocoa/selective_sync_gui.py
maestral_cocoa/settings.py
maestral_cocoa/settings_gui.py
maestral_cocoa/setup.py
maestral_cocoa/setup_gui.py
maestral_cocoa/syncissues.py
maestral_cocoa/updater.py
maestral_cocoa/utils.py
maestral_cocoa/private/__init__.py
maestral_cocoa/private/constants.py
maestral_cocoa/private/dialogs.py
maestral_cocoa/private/platform.py
maestral_cocoa/private/widgets.py
maestral_cocoa/private/implementation/__init__.py
maestral_cocoa/private/implementation/cocoa/__init__.py
maestral_cocoa/private/implementation/cocoa/constants.py
maestral_cocoa/private/implementation/cocoa/dialogs.py
maestral_cocoa/private/implementation/cocoa/factory.py
maestral_cocoa/private/implementation/gtk/__init__.py
maestral_cocoa/private/implementation/gtk/factory.py
maestral_cocoa/resources/__init__.py
maestral_cocoa/resources/faceholder.pdf
maestral_cocoa/resources/maestral.icns
maestral_cocoa/resources/release_notes.css
maestral_cocoa/resources/systray-disconnected.pdf
maestral_cocoa/resources/systray-error.pdf
maestral_cocoa/resources/systray-idle.pdf
maestral_cocoa/resources/systray-info.pdf
maestral_cocoa/resources/systray-paused.pdf
maestral_cocoa/resources/systray-syncing.pdf
maestral_cocoa-1.9.6.dist-info/licenses/LICENSE.txt
maestral_cocoa-1.9.6.dist-info/METADATA
maestral_cocoa-1.9.6.dist-info/WHEEL
maestral_cocoa-1.9.6.dist-info/entry_points.txt
maestral_cocoa-1.9.6.dist-info/top_level.txt
maestral_cocoa-1.9.6.dist-info/RECORD
