Metadata-Version: 2.4
Name: maestral-cocoa
Version: 1.9.6
Summary: Open-source Dropbox client for macOS and Linux.
Home-page: https://maestral.app
Author: Sam Schott
Author-email: sam.schott@outlook.com
Classifier: Operating System :: MacOS
Classifier: Programming Language :: Python
Classifier: Programming Language :: Python :: 3
Classifier: Programming Language :: Python :: 3.8
Classifier: Programming Language :: Python :: 3.9
Classifier: Programming Language :: Python :: 3.10
Classifier: Programming Language :: Python :: 3.11
Classifier: Programming Language :: Python :: 3.12
Classifier: Programming Language :: Python :: 3.13
Classifier: Programming Language :: Python :: 3 :: Only
Requires-Python: >=3.8
License-File: LICENSE.txt
Requires-Dist: click
Requires-Dist: maestral>=1.9.6
Requires-Dist: markdown2
Requires-Dist: toga==0.5.2
Requires-Dist: rubicon-objc==0.5.2
Provides-Extra: dev
Requires-Dist: black; extra == "dev"
Requires-Dist: bump2version; extra == "dev"
Requires-Dist: flake8; extra == "dev"
Requires-Dist: mypy; extra == "dev"
Requires-Dist: pre-commit; extra == "dev"
Requires-Dist: pytest; extra == "dev"
Requires-Dist: pytest-cov; extra == "dev"
Requires-Dist: types-requests; extra == "dev"
Dynamic: license-file
